rustystats-0.3.8.dist-info/METADATA
rustystats-0.3.8.dist-info/WHEEL
rustystats-0.3.8.dist-info/licenses/LICENSE
rustystats/__init__.py
rustystats/_rustystats.cpython-313-x86_64-linux-gnu.so
rustystats/diagnostics.py
rustystats/families.py
rustystats/formula.py
rustystats/glm.py
rustystats/interactions.py
rustystats/links.py
rustystats/regularization_path.py
rustystats/smooth.py
rustystats/splines.py
rustystats/target_encoding.py
rustystats-0.3.8.dist-info/RECORD
