Metadata-Version: 2.4
Name: rustystats
Version: 0.3.8
Classifier: Programming Language :: Rust
Classifier: Programming Language :: Python :: Implementation :: CPython
Classifier: Programming Language :: Python :: 3
Classifier: Programming Language :: Python :: 3.9
Classifier: Programming Language :: Python :: 3.10
Classifier: Programming Language :: Python :: 3.11
Classifier: Programming Language :: Python :: 3.12
Classifier: Topic :: Scientific/Engineering :: Mathematics
Classifier: Intended Audience :: Financial and Insurance Industry
Classifier: Intended Audience :: Science/Research
Requires-Dist: numpy>=1.20
Requires-Dist: polars>=1.0
Requires-Dist: pytest>=7.0 ; extra == 'dev'
Requires-Dist: statsmodels>=0.14 ; extra == 'dev'
Requires-Dist: maturin>=1.4 ; extra == 'dev'
Requires-Dist: jupyter>=1.0 ; extra == 'dev'
Requires-Dist: ipykernel>=6.31.0 ; extra == 'dev'
Requires-Dist: pyarrow>=14.0 ; extra == 'dev'
Requires-Dist: psutil>=5.9 ; extra == 'dev'
Provides-Extra: dev
License-File: LICENSE
Summary: Fast Generalized Linear Models with a Rust backend - statsmodels compatible
Keywords: statistics,glm,actuarial,regression,modeling
License: Elastic-2.0
Requires-Python: >=3.9
Project-URL: Repository, https://github.com/PricingFrontier/rustystats
Project-URL: Documentation, https://github.com/PricingFrontier/rustystats#readme
